dbcopy/__init__.py
dbcopy/cli.py
dbcopy/db.py
dbcopy/util.py
dbcopy-0.1.7.dist-info/LICENSE.txt
dbcopy-0.1.7.dist-info/METADATA
dbcopy-0.1.7.dist-info/WHEEL
dbcopy-0.1.7.dist-info/entry_points.txt
dbcopy-0.1.7.dist-info/top_level.txt
dbcopy-0.1.7.dist-info/RECORD
