Metadata-Version: 2.1
Name: dbcopy
Version: 0.1.7
Summary: Copy contents of a SQL database to another
Home-page: https://github.com/pudo/dbcopy
Author: OCCRP
License: MIT
Platform: UNKNOWN
License-File: LICENSE.txt
Requires-Dist: sqlalchemy
Requires-Dist: stringcase
Requires-Dist: normality
Requires-Dist: click
Requires-Dist: tqdm
Provides-Extra: mssql
Requires-Dist: pyodbc ; extra == 'mssql'
Provides-Extra: mysql
Requires-Dist: PyMySQL ; extra == 'mysql'
Provides-Extra: postgres
Requires-Dist: psycopg2-binary ; extra == 'postgres'
Provides-Extra: postgressql
Requires-Dist: psycopg2-binary ; extra == 'postgressql'
